corai/__init__.py
corai/hp_opti_fct.py
corai/hyper_param_rc_tune.py
corai/src/__init__.py
corai/src/data_processing_fct.py
corai/src/methods_train.py
corai/src/nn_plots.py
corai/src/util_train.py
corai/src/classes/__init__.py
corai/src/classes/fasttensordataloader.py
corai/src/classes/optim_wrapper.py
corai/src/classes/windowcreator.py
corai/src/classes/architecture/__init__.py
corai/src/classes/architecture/conv2dlstm.py
corai/src/classes/architecture/free_nn.py
corai/src/classes/architecture/fully_connected.py
corai/src/classes/architecture/reshape.py
corai/src/classes/architecture/residual_split.py
corai/src/classes/architecture/savable_net.py
corai/src/classes/architecture/rnn/__init__.py
corai/src/classes/architecture/rnn/one_hidden_recurrent.py
corai/src/classes/architecture/rnn/rnn.py
corai/src/classes/architecture/rnn/two_hidden_recurrent.py
corai/src/classes/estimator/__init__.py
corai/src/classes/estimator/estim_benchmark_perf_nn_sizes.py
corai/src/classes/estimator/history/__init__.py
corai/src/classes/estimator/history/estim_history.py
corai/src/classes/estimator/history/plot_estim_history.py
corai/src/classes/estimator/history/relplot_history.py
corai/src/classes/estimator/hyper_parameters/__init__.py
corai/src/classes/estimator/hyper_parameters/distplot_hyper_param.py
corai/src/classes/estimator/hyper_parameters/estim_hyper_param.py
corai/src/classes/estimator/hyper_parameters/plot_estim_hyper_paramm.py
corai/src/classes/estimator/hyper_parameters/relplot_hyper_param.py
corai/src/classes/metric/__init__.py
corai/src/classes/metric/metric.py
corai/src/classes/pl/__init__.py
corai/src/classes/pl/history_dict.py
corai/src/classes/pl/progressbar_without_val_batch_update.py
corai/src/classes/training_stopper/__init__.py
corai/src/classes/training_stopper/early_stopper.py
corai/src/classes/training_stopper/early_stopper_training.py
corai/src/classes/training_stopper/early_stopper_validation.py
corai/src/classes/training_stopper/early_stopper_vanilla.py
corai-1.401.dist-info/LICENSE
corai-1.401.dist-info/METADATA
corai-1.401.dist-info/WHEEL
corai-1.401.dist-info/top_level.txt
corai-1.401.dist-info/RECORD
