Metadata-Version: 2.1
Name: corai
Version: 1.401
Summary: A collection of python libraries.
Home-page: https://github.com/Code-Cornelius/python_libraries
Author: Niels D. Kotlarek, Bianca T. Catea
Author-email: niels.carioukotlarek@gmail.com
License: UNKNOWN
Platform: UNKNOWN
Classifier: Programming Language :: Python :: 3
Classifier: License :: OSI Approved :: MIT License
Classifier: Operating System :: OS Independent
Requires-Python: >=3.7.12
License-File: LICENSE
Requires-Dist: setuptools (>=56.0.0)
Requires-Dist: matplotlib (>=3.3.1)
Requires-Dist: numpy (>=1.21.0)
Requires-Dist: pandas (>=1.2.3)
Requires-Dist: seaborn (>=0.11.1)
Requires-Dist: torch (>=1.8.1+cu102)
Requires-Dist: sklearn (>=0.0)
Requires-Dist: scikit-learn (>=0.23.2)
Requires-Dist: tqdm (>=4.61.1)
Requires-Dist: Keras (>=2.4.3)
Requires-Dist: Pillow (>=8.2.0)
Requires-Dist: scipy (>=1.7.0)
